vsa_cuda.cpython-310-x86_64-linux-gnu.so
vsa/__init__.py
vsa/block_sparse_attn_triton.py
vsa/block_sparse_wrapper.py
vsa/index.py
vsa-0.0.5.dist-info/METADATA
vsa-0.0.5.dist-info/WHEEL
vsa-0.0.5.dist-info/top_level.txt
vsa-0.0.5.dist-info/RECORD
