Metadata-Version: 2.1
Name: vsa
Version: 0.0.5
Summary: Video Sparse Attention Kernel Used in FastVideo
Home-page: https://github.com/hao-ai-lab/FastVideo/tree/main/csrc/attn/video_sparse_attn
Author: Hao AI Lab
License: UNKNOWN
Platform: UNKNOWN
Classifier: Programming Language :: Python :: 3
Classifier: Environment :: GPU :: NVIDIA CUDA :: 12
Classifier: License :: OSI Approved :: Apache Software License
Requires-Python: >=3.10
Requires-Dist: torch>=2.5.0
